pz7z8-0.0.2.data/scripts/dsync
z7z8/__init__.py
pz7z8-0.0.2.dist-info/LICENSE
pz7z8-0.0.2.dist-info/METADATA
pz7z8-0.0.2.dist-info/WHEEL
pz7z8-0.0.2.dist-info/top_level.txt
pz7z8-0.0.2.dist-info/RECORD
