Metadata-Version: 2.1
Name: pz7z8
Version: 0.0.2
Summary: 一些杂乱的小工具集
Author: Chen chuan
Author-email: kcchen@139.com
License: UNKNOWN
Platform: UNKNOWN
Classifier: Programming Language :: Python :: 3
Classifier: License :: OSI Approved :: MIT License
Classifier: Operating System :: OS Independent
Requires-Python: >=3.5
License-File: LICENSE
